Workbook
Name Scenario: Cover!$B$4

Sheet Cover
A1: The Vita Coco Company, Inc. (NASDAQ: COCO) - 3-Statement Model
A2: Built 2026-04-27. Source: FY2025 10-K (accn 0001482981-26-000022) and Q3-2025 10-Q + earnings press releases.
A4: Scenario (1=Bear, 2=Base, 3=Bull): | B4: 2
A6: Key live outputs (recompute when scenario changes):
B7: FY2025A | C7: FY2026E | D7: FY2027E | E7: FY2028E
A8: Net sales ($M) | B8: =IS!B8/1000 | C8: =IS!C8/1000 | D8: =IS!D8/1000 | E8: =IS!E8/1000
A9: YoY growth | C9: =IS!C8/IS!B8-1 | D9: =IS!D8/IS!C8-1 | E9: =IS!E8/IS!D8-1
A10: Gross margin | B10: =IS!B14/IS!B8 | C10: =IS!C14/IS!C8 | D10: =IS!D14/IS!D8 | E10: =IS!E14/IS!E8
A11: Operating margin | B11: =IS!B18/IS!B8 | C11: =IS!C18/IS!C8 | D11: =IS!D18/IS!D8 | E11: =IS!E18/IS!E8
A12: Adj EBITDA ($M) | B12: =IS!B26/1000 | C12: =IS!C26/1000 | D12: =IS!D26/1000 | E12: =IS!E26/1000
A13: Adj EBITDA margin | B13: =IS!B26/IS!B8 | C13: =IS!C26/IS!C8 | D13: =IS!D26/IS!D8 | E13: =IS!E26/IS!E8
A14: Net income ($M) | B14: =IS!B23/1000 | C14: =IS!C23/1000 | D14: =IS!D23/1000 | E14: =IS!E23/1000
A15: Diluted EPS ($) | B15: =IS!B31 | C15: =IS!C31 | D15: =IS!D31 | E15: =IS!E31
A16: FCF ($M) | B16: =CF!B8/1000 | C16: =CF!C8/1000 | D16: =CF!D8/1000 | E16: =CF!E8/1000
A18: Valuation (live):
A19: 12-month price target ($) | B19: =Valuation!B22
A20: Spot price 2026-04-27 ($) | B20: 52.39
A21: Implied upside / (downside) | B21: =B19/B20-1

Sheet Assumptions
A1: Driver | B1: FY26 Bear | C1: FY26 Base | D1: FY26 Bull | E1: FY27 Bear | F1: FY27 Base | G1: FY27 Bull | H1: FY28 Bear | I1: FY28 Base | J1: FY28 Bull | K1: Live FY26 | L1: Live FY27 | M1: Live FY28
A3: REVENUE GROWTH
A4: Americas - Vita Coco Coconut Water (% YoY) | B4: 0.06 | C4: 0.12 | D4: 0.18 | E4: 0.06 | F4: 0.1 | G4: 0.15 | H4: 0.05 | I4: 0.09 | J4: 0.13 | K4: =CHOOSE(Scenario,B4,C4,D4) | L4: =CHOOSE(Scenario,E4,F4,G4) | M4: =CHOOSE(Scenario,H4,I4,J4)
A5: Americas - Private Label (% YoY) | B5: 0.05 | C5: 0.22 | D5: 0.35 | E5: 0.04 | F5: 0.1 | G5: 0.18 | H5: 0.03 | I5: 0.07 | J5: 0.12 | K5: =CHOOSE(Scenario,B5,C5,D5) | L5: =CHOOSE(Scenario,E5,F5,G5) | M5: =CHOOSE(Scenario,H5,I5,J5)
A6: Americas - Other (% YoY) | B6: -0.1 | C6: 0.1 | D6: 0.3 | E6: 0.05 | F6: 0.1 | G6: 0.2 | H6: 0.05 | I6: 0.08 | J6: 0.15 | K6: =CHOOSE(Scenario,B6,C6,D6) | L6: =CHOOSE(Scenario,E6,F6,G6) | M6: =CHOOSE(Scenario,H6,I6,J6)
A7: International - Vita Coco Coconut Water (% YoY) | B7: 0.18 | C7: 0.3 | D7: 0.4 | E7: 0.15 | F7: 0.25 | G7: 0.35 | H7: 0.12 | I7: 0.22 | J7: 0.3 | K7: =CHOOSE(Scenario,B7,C7,D7) | L7: =CHOOSE(Scenario,E7,F7,G7) | M7: =CHOOSE(Scenario,H7,I7,J7)
A8: International - Private Label (% YoY) | B8: 0.05 | C8: 0.15 | D8: 0.25 | E8: 0.05 | F8: 0.12 | G8: 0.2 | H8: 0.05 | I8: 0.1 | J8: 0.15 | K8: =CHOOSE(Scenario,B8,C8,D8) | L8: =CHOOSE(Scenario,E8,F8,G8) | M8: =CHOOSE(Scenario,H8,I8,J8)
A9: International - Other (% YoY) | B9: -0.2 | C9: 0 | D9: 0.2 | E9: 0 | F9: 0.05 | G9: 0.15 | H9: 0 | I9: 0.05 | J9: 0.1 | K9: =CHOOSE(Scenario,B9,C9,D9) | L9: =CHOOSE(Scenario,E9,F9,G9) | M9: =CHOOSE(Scenario,H9,I9,J9)
A11: GROSS MARGIN
A12: Americas gross margin (%) | B12: 0.355 | C12: 0.385 | D12: 0.4 | E12: 0.355 | F12: 0.39 | G12: 0.41 | H12: 0.355 | I12: 0.39 | J12: 0.415 | K12: =CHOOSE(Scenario,B12,C12,D12) | L12: =CHOOSE(Scenario,E12,F12,G12) | M12: =CHOOSE(Scenario,H12,I12,J12)
A13: International gross margin (%) | B13: 0.33 | C13: 0.36 | D13: 0.385 | E13: 0.335 | F13: 0.37 | G13: 0.4 | H13: 0.34 | I13: 0.375 | J13: 0.405 | K13: =CHOOSE(Scenario,B13,C13,D13) | L13: =CHOOSE(Scenario,E13,F13,G13) | M13: =CHOOSE(Scenario,H13,I13,J13)
A15: OPEX & MISC
A16: SG&A as % of net sales | B16: 0.235 | C16: 0.22 | D16: 0.21 | E16: 0.23 | F16: 0.215 | G16: 0.205 | H16: 0.225 | I16: 0.21 | J16: 0.2 | K16: =CHOOSE(Scenario,B16,C16,D16) | L16: =CHOOSE(Scenario,E16,F16,G16) | M16: =CHOOSE(Scenario,H16,I16,J16)
A17: Effective tax rate (%) | B17: 0.25 | C17: 0.23 | D17: 0.215 | E17: 0.25 | F17: 0.23 | G17: 0.215 | H17: 0.25 | I17: 0.23 | J17: 0.215 | K17: =CHOOSE(Scenario,B17,C17,D17) | L17: =CHOOSE(Scenario,E17,F17,G17) | M17: =CHOOSE(Scenario,H17,I17,J17)
A18: D&A as % of net sales | B18: 0.002 | C18: 0.002 | D18: 0.002 | E18: 0.002 | F18: 0.002 | G18: 0.002 | H18: 0.002 | I18: 0.002 | J18: 0.002 | K18: =CHOOSE(Scenario,B18,C18,D18) | L18: =CHOOSE(Scenario,E18,F18,G18) | M18: =CHOOSE(Scenario,H18,I18,J18)
A19: Stock-based comp as % of net sales | B19: 0.018 | C19: 0.018 | D19: 0.018 | E19: 0.018 | F19: 0.018 | G19: 0.018 | H19: 0.018 | I19: 0.018 | J19: 0.018 | K19: =CHOOSE(Scenario,B19,C19,D19) | L19: =CHOOSE(Scenario,E19,F19,G19) | M19: =CHOOSE(Scenario,H19,I19,J19)
A20: Capex as % of net sales | B20: 0.002 | C20: 0.002 | D20: 0.002 | E20: 0.002 | F20: 0.002 | G20: 0.002 | H20: 0.002 | I20: 0.002 | J20: 0.002 | K20: =CHOOSE(Scenario,B20,C20,D20) | L20: =CHOOSE(Scenario,E20,F20,G20) | M20: =CHOOSE(Scenario,H20,I20,J20)
A21: Net working capital as % of Delta rev | B21: 0.2 | C21: 0.2 | D21: 0.2 | E21: 0.2 | F21: 0.2 | G21: 0.2 | H21: 0.2 | I21: 0.2 | J21: 0.2 | K21: =CHOOSE(Scenario,B21,C21,D21) | L21: =CHOOSE(Scenario,E21,F21,G21) | M21: =CHOOSE(Scenario,H21,I21,J21)
A22: Diluted shares outstanding (M) | B22: 60 | C22: 60 | D22: 60 | E22: 60.5 | F22: 60 | G22: 59.5 | H22: 61 | I22: 60 | J22: 59 | K22: =CHOOSE(Scenario,B22,C22,D22) | L22: =CHOOSE(Scenario,E22,F22,G22) | M22: =CHOOSE(Scenario,H22,I22,J22)
A23: Non-operating income ($M) | B23: 0 | C23: 5 | D23: 10 | E23: 0 | F23: 5 | G23: 10 | H23: 0 | I23: 5 | J23: 10 | K23: =CHOOSE(Scenario,B23,C23,D23) | L23: =CHOOSE(Scenario,E23,F23,G23) | M23: =CHOOSE(Scenario,H23,I23,J23)
A25: VALUATION
A26: Exit EV/EBITDA multiple (FY27) | B26: 12 | C26: 17 | D26: 22 | E26: 12 | F26: 17 | G26: 22 | H26: 12 | I26: 17 | J26: 22 | K26: =CHOOSE(Scenario,B26,C26,D26) | L26: =CHOOSE(Scenario,E26,F26,G26) | M26: =CHOOSE(Scenario,H26,I26,J26)
A27: WACC (%) | B27: 0.1 | C27: 0.09 | D27: 0.08 | E27: 0.1 | F27: 0.09 | G27: 0.08 | H27: 0.1 | I27: 0.09 | J27: 0.08 | K27: =CHOOSE(Scenario,B27,C27,D27) | L27: =CHOOSE(Scenario,E27,F27,G27) | M27: =CHOOSE(Scenario,H27,I27,J27)
A28: Terminal growth rate (%) | B28: 0.02 | C28: 0.025 | D28: 0.03 | E28: 0.02 | F28: 0.025 | G28: 0.03 | H28: 0.02 | I28: 0.025 | J28: 0.03 | K28: =CHOOSE(Scenario,B28,C28,D28) | L28: =CHOOSE(Scenario,E28,F28,G28) | M28: =CHOOSE(Scenario,H28,I28,J28)
A29: Cash at FY25 ($M) | B29: 197 | C29: 197 | D29: 197 | E29: 197 | F29: 197 | G29: 197 | H29: 197 | I29: 197 | J29: 197 | K29: =CHOOSE(Scenario,B29,C29,D29) | L29: =CHOOSE(Scenario,E29,F29,G29) | M29: =CHOOSE(Scenario,H29,I29,J29)
A30: Debt at FY25 ($M) | B30: 0 | C30: 0 | D30: 0 | E30: 0 | F30: 0 | G30: 0 | H30: 0 | I30: 0 | J30: 0 | K30: =CHOOSE(Scenario,B30,C30,D30) | L30: =CHOOSE(Scenario,E30,F30,G30) | M30: =CHOOSE(Scenario,H30,I30,J30)

Sheet History
A1: ($000s unless noted) | B1: FY2019A | C1: FY2020A | D1: FY2021A | E1: FY2022A | F1: FY2023A | G1: FY2024A | H1: FY2025A
A2: Net sales | B2: 283949000 | C2: 310644000 | D2: 379513000 | E2: 427787000 | F2: 493612000 | G2: 516013000 | H2: 609780000
A3: COGS | B3: 190961000 | C3: 205786000 | D3: 266365000 | E3: 324426000 | F3: 312883000 | G3: 317230000 | H3: 387185000
A4: Gross profit | B4: 92988000 | C4: 104858000 | D4: 113148000 | E4: 103361000 | F4: 180729000 | G4: 198783000 | H4: 222595000
A5: Gross margin | B5: 0.32748134 | C5: 0.33755038 | D5: 0.29813998 | E5: 0.24161791 | F5: 0.36613575 | G5: 0.38522867 | H5: 0.36504149
A6: SG&A | B6: 78917000 | C6: 74401000 | D6: 88559000 | E6: 100306000 | F6: 124236000 | G6: 124963000 | H6: 140063000
A7: Operating income | B7: 13371000 | C7: 46857000 | D7: 24589000 | E7: 3055000 | F7: 56493000 | G7: 73820000 | H7: 82532000
A8: Operating margin | B8: 0.047089442 | C8: 0.15083826 | D8: 0.064790929 | E8: 0.0071414045 | F8: 0.11444819 | G8: 0.14305841 | H8: 0.13534717
A9: Net income | B9: 9417000 | C9: 32660000 | D9: 19015000 | E9: 7814000 | F9: 46629000 | G9: 55952000 | H9: 71320000
A10: Net margin | B10: 0.033164406 | C10: 0.10513643 | D10: 0.050103686 | E10: 0.0182661 | F10: 0.094464883 | G10: 0.10843138 | H10: 0.11696022
A11: Diluted EPS | B11: 0.16 | C11: 0.56 | D11: 0.35 | E11: 0.14 | F11: 0.79 | G11: 0.94 | H11: 1.19
A12: Diluted shares (M) | B12: 57.15255 | C12: 58.610825 | D12: 54.186121 | E12: 56.123661 | F12: 58.747338 | G12: 59.286562 | H12: 59.967691
A13: CFO | B13: 21765000 | C13: 33323000 | D13: -16166000 | E13: -10935000 | F13: 107155000 | G13: 42899000 | H13: 47174000
... A15: FCF (CFO - Capex) | B15: 20756000 | C15: 32931000 | D15: -16723000 | E15: -11917000 | F15: 106556000 | G15: 41925000 | H15: 39025000
A16: Cash & equivalents | C16: 72181000 | D16: 28690000 | E16: 19629000 | F16: 132537000 | G16: 164669000 | H16: 196873000
A17: Inventory | C17: 31967000 | D17: 75360000 | E17: 84115000 | F17: 50757000 | G17: 83600000 | H17: 111468000
A18: Accounts receivable | C18: 30504000 | D18: 47195000 | E18: 43350000 | F18: 50086000 | G18: 63450000 | H18: 81514000
A19: Total assets | C19: 183861000 | D19: 197484000 | E19: 197757000 | F19: 285682000 | G19: 362381000 | H19: 461158000
A20: Stockholders' equity | C20: 102221000 | D20: 123173000 | E20: 141093000 | F20: 202437000 | G20: 258817000 | H20: 331542000
A22: Source: extracted/annual.csv (XBRL companyfacts) -- backed by 10-Ks in raw/filings/
A24: Net sales by segment x brand ($000s)
B25: FY2022A | C25: FY2023A | D25: FY2024A | E25: FY2025A
A26: Americas - Vita Coco Coconut Water | B26: 275964 | C26: 317221 | D26: 343288 | E26: 424319
A27: Americas - Private Label | B27: 88173 | C27: 103166 | D27: 89900 | E27: 62731
A28: Americas - Other | B28: 9485 | C28: 9858 | D28: 9155 | E28: 21723
A29: Americas subtotal | B29: 373622 | C29: 430245 | D29: 442343 | E29: 508773
A30: International - Vita Coco Coconut Water | B30: 38570 | C30: 41829 | D30: 50318 | E30: 71943
A31: International - Private Label | B31: 12855 | C31: 18713 | D31: 19324 | E31: 25951
A32: International - Other | B32: 2740 | C32: 2825 | D32: 4028 | E32: 3113
A33: International subtotal | B33: 54165 | C33: 63367 | D33: 73670 | E33: 101007
A35: Source: extracted/segment_history.csv (parsed from 8-K Ex 99.1 press releases)

Sheet IS
A1: INCOME STATEMENT ($000s) | B1: FY2025A | C1: FY2026E | D1: FY2027E | E1: FY2028E
A2: Americas - Vita Coco Coconut Water | B2: 424319 | C2: =B2*(1+Assumptions!K4) | D2: =C2*(1+Assumptions!L4) | E2: =D2*(1+Assumptions!M4)
A3: Americas - Private Label | B3: 62731 | C3: =B3*(1+Assumptions!K5) | D3: =C3*(1+Assumptions!L5) | E3: =D3*(1+Assumptions!M5)
A4: Americas - Other | B4: 21723 | C4: =B4*(1+Assumptions!K6) | D4: =C4*(1+Assumptions!L6) | E4: =D4*(1+Assumptions!M6)
A5: International - Vita Coco Coconut Water | B5: 71943 | C5: =B5*(1+Assumptions!K7) | D5: =C5*(1+Assumptions!L7) | E5: =D5*(1+Assumptions!M7)
A6: International - Private Label | B6: 25951 | C6: =B6*(1+Assumptions!K8) | D6: =C6*(1+Assumptions!L8) | E6: =D6*(1+Assumptions!M8)
A7: International - Other | B7: 3113 | C7: =B7*(1+Assumptions!K9) | D7: =C7*(1+Assumptions!L9) | E7: =D7*(1+Assumptions!M9)
A8: Net sales (total) | B8: =SUM(B2:B7) | C8: =SUM(C2:C7) | D8: =SUM(D2:D7) | E8: =SUM(E2:E7)
A10: Americas subtotal | B10: =SUM(B2:B4) | C10: =SUM(C2:C4) | D10: =SUM(D2:D4) | E10: =SUM(E2:E4)
A11: International subtotal | B11: =SUM(B5:B7) | C11: =SUM(C5:C7) | D11: =SUM(D5:D7) | E11: =SUM(E5:E7)
A12: GP - Americas | B12: 187309 | C12: =C10*Assumptions!K12 | D12: =D10*Assumptions!L12 | E12: =E10*Assumptions!M12
A13: GP - International | B13: 35286 | C13: =C11*Assumptions!K13 | D13: =D11*Assumptions!L13 | E13: =E11*Assumptions!M13
A14: Gross profit | B14: =B12+B13 | C14: =C12+C13 | D14: =D12+D13 | E14: =E12+E13
A15: Gross margin | B15: =B14/B8 | C15: =C14/C8 | D15: =D14/D8 | E15: =E14/E8
A17: SG&A | B17: 140063 | C17: =C8*Assumptions!K16 | D17: =D8*Assumptions!L16 | E17: =E8*Assumptions!M16
A18: Operating income | B18: =B14-B17 | C18: =C14-C17 | D18: =D14-D17 | E18: =E14-E17
A19: Operating margin | B19: =B18/B8 | C19: =C18/C8 | D19: =D18/D8 | E19: =E18/E8
A20: Non-operating income (FX/int.) | B20: 10439 | C20: =Assumptions!K23*1000 | D20: =Assumptions!L23*1000 | E20: =Assumptions!M23*1000
A21: Pretax income | B21: =B18+B20 | C21: =C18+C20 | D21: =D18+D20 | E21: =E18+E20
A22: Income tax | B22: 21651 | C22: =C21*Assumptions!K17 | D22: =D21*Assumptions!L17 | E22: =E21*Assumptions!M17
A23: Net income | B23: =B21-B22 | C23: =C21-C22 | D23: =D21-D22 | E23: =E21-E22
A24: D&A (memo) | B24: 1072 | C24: =C8*Assumptions!K18 | D24: =D8*Assumptions!L18 | E24: =E8*Assumptions!M18
A25: Stock-based comp (memo) | B25: 10843 | C25: =C8*Assumptions!K19 | D25: =D8*Assumptions!L19 | E25: =E8*Assumptions!M19
A26: Adj EBITDA | B26: =B18+B24+B25 | C26: =C18+C24+C25 | D26: =D18+D24+D25 | E26: =E18+E24+E25
A27: Adj EBITDA margin | B27: =B26/B8 | C27: =C26/C8 | D27: =D26/D8 | E27: =E26/E8
A29: Diluted shares (M) | B29: 59.967691 | C29: =Assumptions!K22 | D29: =Assumptions!L22 | E29: =Assumptions!M22
A31: Diluted EPS | B31: =B23/B29/1000 | C31: =C23/C29/1000 | D31: =D23/D29/1000 | E31: =E23/E29/1000

Sheet BS
A1: BALANCE SHEET ($000s) | B1: FY2025A | C1: FY2026E | D1: FY2027E | E1: FY2028E
A2: Cash & equivalents | B2: 196873 | C2: =B2+CF!C11 | D2: =C2+CF!D11 | E2: =D2+CF!E11
A3: Accounts receivable | B3: 81514 | C3: =IS!C8*0.133678 | D3: =IS!D8*0.133678 | E3: =IS!E8*0.133678
A4: Inventory | B4: 111468 | C4: =IS!C8*0.182800 | D4: =IS!D8*0.182800 | E4: =IS!E8*0.182800
A5: Other current assets | B5: 31585 | C5: =IS!C8*0.051797 | D5: =IS!D8*0.051797 | E5: =IS!E8*0.051797
A6: Total current assets | B6: =SUM(B2:B5) | C6: =SUM(C2:C5) | D6: =SUM(D2:D5) | E6: =SUM(E2:E5)
A7: PP&E + intangibles + other | B7: 39718 | C7: =IS!C8*0.065135 | D7: =IS!D8*0.065135 | E7: =IS!E8*0.065135
A8: TOTAL ASSETS | B8: =B6+B7 | C8: =C6+C7 | D8: =D6+D7 | E8: =E6+E7
A9: Accounts payable | B9: 25464 | C9: =IS!C8*0.041759 | D9: =IS!D8*0.041759 | E9: =IS!E8*0.041759
A10: Other current liab | B10: 90968 | C10: =IS!C8*0.149182 | D10: =IS!D8*0.149182 | E10: =IS!E8*0.149182
A11: Non-current liab | B11: 13184 | C11: =IS!C8*0.021621 | D11: =IS!D8*0.021621 | E11: =IS!E8*0.021621
A12: TOTAL LIABILITIES | B12: =SUM(B9:B11) | C12: =SUM(C9:C11) | D12: =SUM(D9:D11) | E12: =SUM(E9:E11)
A13: Stockholders' equity | B13: 331542 | C13: =B13+IS!C23-15000 | D13: =C13+IS!D23-15000 | E13: =D13+IS!E23-15000
A14: TOTAL LIAB. & EQUITY | B14: =B12+B13 | C14: =C12+C13 | D14: =D12+D13 | E14: =E12+E13
A15: Check (Assets - L&E) | B15: =B8-B14 | C15: =C8-C14 | D15: =D8-D14 | E15: =E8-E14

Sheet CF
A1: CASH FLOW ($000s) | B1: FY2025A | C1: FY2026E | D1: FY2027E | E1: FY2028E
A2: Net income | B2: =IS!B23 | C2: =IS!C23 | D2: =IS!D23 | E2: =IS!E23
A3: D&A | B3: 1072 | C3: =IS!C24 | D3: =IS!D24 | E3: =IS!E24
A4: Stock-based comp | B4: 10843 | C4: =IS!C25 | D4: =IS!D25 | E4: =IS!E25
A5: Δ Net working capital | B5: -16500 | C5: =-Assumptions!K21*(IS!C8-IS!B8) | D5: =-Assumptions!L21*(IS!D8-IS!C8) | E5: =-Assumptions!M21*(IS!E8-IS!D8)
A6: CFO | B6: =B2+B3+B4+B5 | C6: =C2+C3+C4+C5 | D6: =D2+D3+D4+D5 | E6: =E2+E3+E4+E5
A7: Capex | B7: -8149 | C7: =-IS!C8*Assumptions!K20 | D7: =-IS!D8*Assumptions!L20 | E7: =-IS!E8*Assumptions!M20
A8: FCF | B8: =B6+B7 | C8: =C6+C7 | D8: =D6+D7 | E8: =E6+E7
A9: Repurchases | B9: -11341 | C9: -15000 | D9: -15000 | E9: -15000
A10: Dividends | B10: 0 | C10: 0 | D10: 0 | E10: 0
A11: Other (FX, etc.) | B11: 0 | C11: 0 | D11: 0 | E11: 0
A12: Net Δ cash | B12: =B8+B9+B10+B11 | C12: =C8+C9+C10+C11 | D12: =D8+D9+D10+D11 | E12: =E8+E9+E10+E11

Sheet Valuation
A1: VALUATION | B1: FY2026E | C1: FY2027E | D1: FY2028E
A2: Adj EBITDA ($M) | B2: =IS!C26/1000 | C2: =IS!D26/1000 | D2: =IS!E26/1000
A3: Net income ($M) | B3: =IS!C23/1000 | C3: =IS!D23/1000 | D3: =IS!E23/1000
A4: FCF ($M) | B4: =CF!C8/1000 | C4: =CF!D8/1000 | D4: =CF!E8/1000
A6: EXIT EV/EBITDA APPROACH (anchor)
A7: Exit multiple on FY27E EBITDA | B7: =Assumptions!L26
A8: Implied EV at end of FY27 ($M) | B8: =C2*Assumptions!L26
A9: (+) Cash at end of FY27 ($M) | B9: =Assumptions!L29+B4+C4-15-15
A10: (-) Debt ($M) | B10: =Assumptions!L30
A11: Equity value at end of FY27 ($M) | B11: =B8+B9-B10
A12: Diluted shares (M) | B12: =Assumptions!L22
A13: Implied price at end of FY27 ($) | B13: =B11/B12
A15: WACC (for discount) | B15: =Assumptions!L27
A16: Discount window: end FY27 -> Apr 2027 (~8 months)
A18: 12-MONTH PRICE TARGET (LIVE)
A19: Approach: Equity value at end FY27 / shares, discount to Apr 2027 (12m fwd)
A20: Discount factor = 1/(1+WACC)^0.67
A21: Discounted equity value ($M) | B21: =B11/(1+B15)^0.67
A22: 12-MONTH PRICE TARGET ($) | B22: =B21/B12
A24: CROSS-CHECK: P/E
A25: FY27E EPS ($) | B25: =IS!D31
A26: P/E target on FY27 EPS | B26: 30
A27: Implied price at end FY27 ($) | B27: =B25*B26
A28: Discounted to Apr 2027 (12m fwd) at WACC | B28: =B27/(1+B15)^0.67
A30: CROSS-CHECK: DCF (Gordon growth on FY28 FCF)
A31: FY28E FCF ($M) | B31: =D4
A32: WACC (%) | B32: =B15
A33: Terminal growth (%) | B33: =Assumptions!L28
A34: Terminal value at end FY28 ($M) | B34: =B31*(1+B33)/(B32-B33)
A35: PV of FY26-28 FCF ($M) | B35: =B4/(1+B15)^0.5+C4/(1+B15)^1.5+D4/(1+B15)^2.5
A36: PV of terminal value ($M) | B36: =B34/(1+B15)^3.0
A37: Enterprise value (DCF) ($M) | B37: =B35+B36
A38: (+) Cash now ($M) | B38: =Assumptions!L29
A39: Equity value (DCF) ($M) | B39: =B37+B38
A40: DCF price per share ($) | B40: =B39/B12
